vulkan/__init__.py
vulkan/_vulkan.py
vulkan/_vulkancache.py
vulkan/vulkan.cdef.h
vulkan/vulkan_build.py
chturne_vulkan-1.1.99.2.dist-info/LICENSE
chturne_vulkan-1.1.99.2.dist-info/METADATA
chturne_vulkan-1.1.99.2.dist-info/WHEEL
chturne_vulkan-1.1.99.2.dist-info/top_level.txt
chturne_vulkan-1.1.99.2.dist-info/RECORD
