Metadata-Version: 2.1
Name: chturne-vulkan
Version: 1.1.99.2
Summary: Ultimate Python binding for Vulkan API
Home-page: https://github.com/charlie-ht/vulkan
Author: realitix
Author-email: realitix@gmail.com
License: UNKNOWN
Keywords: Graphics,3D,Vulkan,cffi
Platform: UNKNOWN
Classifier: Development Status :: 5 - Production/Stable
Classifier: Intended Audience :: Developers
Classifier: License :: OSI Approved :: Apache Software License
Classifier: Operating System :: Android
Classifier: Operating System :: Microsoft :: Windows
Classifier: Operating System :: POSIX :: Linux
Classifier: Natural Language :: English
Classifier: Topic :: Multimedia :: Graphics
Classifier: Topic :: Scientific/Engineering
Classifier: Topic :: Software Development :: Libraries :: Python Modules
License-File: LICENSE
Requires-Dist: cffi (>=1.10)
